converter/Converter.py
converter/__init__.py
converter/aruba/__init__.py
converter/aruba/parser/ArubaProjectParser.py
converter/aruba/parser/__init__.py
dnac/DnacCluster.py
dnac/__init__.py
dnac/_init_.py
dnac/dnac_utils.py
dnac/converter/Converter.py
dnac/converter/__init__.py
dnac/converter/aruba/__init__.py
dnac/converter/aruba/parser/ArubaProjectParser.py
dnac/converter/aruba/parser/__init__.py
dnac/emitter/__init__.py
dnac/emitter/deployment/MapHierarchyDeployer.py
dnac/emitter/deployment/__init__.py
dnac/emitter/persistance/__init__.py
dnac/exception/BadProjectFileException.py
dnac/exception/DnacException.py
dnac/exception/DuplicateFloorException.py
dnac/exception/InvalidCriterionException.py
dnac/exception/InvalidUserException.py
dnac/exception/NoSessionException.py
dnac/exception/OperationNotPermittedException.py
dnac/exception/__init__.py
dnac/exception/_init_.py
dnac/maglev/__init__.py
dnac/maglev/_init_.py
dnac/maglev/factory/MaglevFactory.py
dnac/maglev/factory/__init__.py
dnac/maglev/factory/_init_.py
dnac/maglev/kernel/MaglevKernel.py
dnac/maglev/kernel/__init__.py
dnac/maglev/security/SecurityManager.py
dnac/maglev/security/Session.py
dnac/maglev/security/__init__.py
dnac/maglev/security/_init_.py
dnac/maglev/security/role/ResourceType.py
dnac/maglev/security/role/Role.py
dnac/maglev/security/role/RoleManager.py
dnac/maglev/security/role/__init__.py
dnac/maglev/security/role/_init_.py
dnac/maglev/security/role/factory/RoleFactory.py
dnac/maglev/security/role/factory/__init__.py
dnac/maglev/security/role/factory/_init_.py
dnac/maglev/security/user/User.py
dnac/maglev/security/user/UserManager.py
dnac/maglev/security/user/__init__.py
dnac/maglev/security/user/_init_.py
dnac/maglev/task/Task.py
dnac/maglev/task/TaskManager.py
dnac/maglev/task/__init__.py
dnac/maglev/task/_init_.py
dnac/model/__init__.py
dnac/model/network/AccessPoint.py
dnac/model/network/PAP.py
dnac/model/network/__init__.py
dnac/platform/DnacPlatform.py
dnac/platform/__init__.py
dnac_shell-0.1.2.dist-info/METADATA
dnac_shell-0.1.2.dist-info/WHEEL
dnac_shell-0.1.2.dist-info/top_level.txt
dnac_shell-0.1.2.dist-info/RECORD
