Metadata-Version: 2.1
Name: dnac-shell
Version: 0.1.2
Summary: DNAC Command Line Shell that can be used to perform salient operations on DNAC
Home-page: UNKNOWN
Author: Rk Somasundaram
Author-email: rks@cisco.com
Maintainer: Rk Somasundaram
License: cisco Systems Inc.
Download-URL: http://www.cisco.com
Platform: UNKNOWN
Requires-Dist: PyYAML
Requires-Dist: requests
